ChangeLog
LICENSE
Makefile
README.md
README.rst
requirements.txt
requirements_dev.txt
setup.cfg
setup.py
scrapy_mysql_pipeline/__init__.py
scrapy_mysql_pipeline/pipeline.py
scrapy_mysql_pipeline.egg-info/PKG-INFO
scrapy_mysql_pipeline.egg-info/SOURCES.txt
scrapy_mysql_pipeline.egg-info/dependency_links.txt
scrapy_mysql_pipeline.egg-info/not-zip-safe
scrapy_mysql_pipeline.egg-info/pbr.json
scrapy_mysql_pipeline.egg-info/requires.txt
scrapy_mysql_pipeline.egg-info/top_level.txt