Metadata-Version: 1.1
Name: scrapy-mysql-pipeline
Version: 2019.7.19
Summary: Asynchronous mysql Scrapy item pipeline
Home-page: https://github.com/IaroslavR/scrapy-mysql-pipeline
Author: Iaroslav Russkykh
Author-email: iarruss@ya.ru
License: MIT
Platform: UNKNOWN
Classifier: Development Status :: 4 - Beta
Classifier: Framework :: Scrapy
Classifier: Intended Audience :: Developers
Classifier: License :: OSI Approved :: MIT License
Classifier: Operating System :: OS Independent
Classifier: Programming Language :: Python
Classifier: Topic :: Internet :: WWW/HTTP
